mmcifar/__init__.py
mmcifar/datasets.py
mmcifar/transforms.py
mmcifar-0.0.3.dist-info/licenses/LICENSE
mmcifar-0.0.3.dist-info/METADATA
mmcifar-0.0.3.dist-info/WHEEL
mmcifar-0.0.3.dist-info/top_level.txt
mmcifar-0.0.3.dist-info/RECORD
