Metadata-Version: 2.4
Name: mmcifar
Version: 0.0.3
Summary: A dataset wrapper that performs CIFAR-10 multimodal loading
Author: Michigan Synthetic Biology Team
License: MIT
Project-URL: Homepage, https://github.com/umsynbio/MM_CIFAR
Project-URL: Repository, https://github.com/umsynbio/MM_CIFAR
Project-URL: Documentation, https://github.com/umsynbio/MM_CIFAR#readme
Classifier: Development Status :: 3 - Alpha
Classifier: Intended Audience :: Developers
Classifier: Intended Audience :: Science/Research
Classifier: License :: OSI Approved :: MIT License
Classifier: Programming Language :: Python :: 3.11
Classifier: Programming Language :: Python :: 3.12
Requires-Python: >=3.11
License-File: LICENSE
Requires-Dist: torch
Requires-Dist: torchvision
Requires-Dist: matplotlib
Provides-Extra: dev
Requires-Dist: pytest>=6.0; extra == "dev"
Dynamic: license-file
